.gitignore
LICENSE.txt
README.md
setup.cfg
setup.py
siridb/__init__.py
siridb/connector/__init__.py
siridb/connector/lib/__init__.py
siridb/connector/lib/client.py
siridb/connector/lib/connection.py
siridb/connector/lib/constants.py
siridb/connector/lib/datapackage.py
siridb/connector/lib/defaults.py
siridb/connector/lib/exceptions.py
siridb/connector/lib/logging.py
siridb/connector/lib/protocol.py
siridb/connector/lib/protomap.py
siridb_connector.egg-info/PKG-INFO
siridb_connector.egg-info/SOURCES.txt
siridb_connector.egg-info/dependency_links.txt
siridb_connector.egg-info/requires.txt
siridb_connector.egg-info/top_level.txt