Metadata-Version: 2.1
Name: siridb-connector
Version: 2.1.0
Summary: SiriDB Connector
Home-page: https://github.com/SiriDB/siridb-connector
Author: Jeroen van der Heijden
Author-email: jeroen@cesbit.com
License: UNKNOWN
Download-URL: https://github.com/SiriDB/siridb-connector/tarball/2.1.0
Keywords: siridb,connector,database,client
Platform: UNKNOWN
Classifier: Development Status :: 4 - Beta
Classifier: Environment :: Other Environment
Classifier: Intended Audience :: Developers
Classifier: License :: OSI Approved :: MIT License
Classifier: Operating System :: OS Independent
Classifier: Programming Language :: Python :: 3
Classifier: Programming Language :: Python :: 3.5
Classifier: Programming Language :: Python :: 3.6
Classifier: Programming Language :: Python :: 3.7
Classifier: Programming Language :: Python :: 3.8
Classifier: Programming Language :: Python :: 3 :: Only
Classifier: Topic :: Database
Classifier: Topic :: Software Development
